{"root":[{"name":"Assembly-CSharp","path":"C:\\Users\\merli\\Desktop\\Unity3D_And_Node.JS_Multi-Player_English\\Client\\Library\\ScriptAssemblies\\Assembly-CSharp.dll","types":[{"className":"Networking","fieldInfos":[{"name":"data","type":"System.Byte[]","flags":{"value__":0},"fixedBufferLength":0,"fixedBufferTypename":null},{"name":"running","type":"System.Boolean","flags":{"value__":0},"fixedBufferLength":0,"fixedBufferTypename":null},{"name":"id","type":"System.String","flags":{"value__":0},"fixedBufferLength":0,"fixedBufferTypename":null},{"name":"reading","type":"System.Boolean","flags":{"value__":0},"fixedBufferLength":0,"fixedBufferTypename":null},{"name":"writing","type":"System.Boolean","flags":{"value__":0},"fixedBufferLength":0,"fixedBufferTypename":null},{"name":"searchingMatch","type":"System.Boolean","flags":{"value__":0},"fixedBufferLength":0,"fixedBufferTypename":null},{"name":"connected","type":"System.Boolean","flags":{"value__":0},"fixedBufferLength":0,"fixedBufferTypename":null}]}]},{"name":"UnityEngine.TestRunner","path":"C:\\Users\\merli\\Desktop\\Unity3D_And_Node.JS_Multi-Player_English\\Client\\Library\\ScriptAssemblies\\UnityEngine.TestRunner.dll","types":[{"className":"UnityEngine.TestRunner.Utils.TestRunCallbackListener","fieldInfos":[]},{"className":"UnityEngine.TestRunner.TestLaunchers.RemoteTestData","fieldInfos":[{"name":"id","type":"System.String","flags":{"value__":0},"fixedBufferLength":0,"fixedBufferTypename":null},{"name":"name","type":"System.String","flags":{"value__":0},"fixedBufferLength":0,"fixedBufferTypename":null},{"name":"fullName","type":"System.String","flags":{"value__":0},"fixedBufferLength":0,"fixedBufferTypename":null},{"name":"testCaseCount","type":"System.Int32","flags":{"value__":0},"fixedBufferLength":0,"fixedBufferTypename":null},{"name":"ChildIndex","type":"System.Int32","flags":{"value__":0},"fixedBufferLength":0,"fixedBufferTypename":null},{"name":"hasChildren","type":"System.Boolean","flags":{"value__":0},"fixedBufferLength":0,"fixedBufferTypename":null},{"name":"isSuite","type":"System.Boolean","flags":{"value__":0},"fixedBufferLength":0,"fixedBufferTypename":null},{"name":"childrenIds","type":"System.String[]","flags":{"value__":0},"fixedBufferLength":0,"fixedBufferTypename":null},{"name":"testCaseTimeout","type":"System.Int32","flags":{"value__":0},"fixedBufferLength":0,"fixedBufferTypename":null},{"name":"Categories","type":"System.String[]","flags":{"value__":0},"fixedBufferLength":0,"fixedBufferTypename":null},{"name":"IsTestAssembly","type":"System.Boolean","flags":{"value__":0},"fixedBufferLength":0,"fixedBufferTypename":null},{"name":"RunState","type":"NUnit.Framework.Interfaces.RunState","flags":{"value__":0},"fixedBufferLength":0,"fixedBufferTypename":null},{"name":"Description","type":"System.String","flags":{"value__":0},"fixedBufferLength":0,"fixedBufferTypename":null},{"name":"SkipReason","type":"System.String","flags":{"value__":0},"fixedBufferLength":0,"fixedBufferTypename":null},{"name":"ParentId","type":"System.String","flags":{"value__":0},"fixedBufferLength":0,"fixedBufferTypename":null},{"name":"UniqueName","type":"System.String","flags":{"value__":0},"fixedBufferLength":0,"fixedBufferTypename":null},{"name":"ParentUniqueName","type":"System.String","flags":{"value__":0},"fixedBufferLength":0,"fixedBufferTypename":null},{"name":"ParentFullName","type":"System.String","flags":{"value__":0},"fixedBufferLength":0,"fixedBufferTypename":null}]},{"className":"UnityEngine.TestRunner.TestLaunchers.RemoteTestResultData","fieldInfos":[{"name":"testId","type":"System.String","flags":{"value__":0},"fixedBufferLength":0,"fixedBufferTypename":null},{"name":"name","type":"System.String","flags":{"value__":0},"fixedBufferLength":0,"fixedBufferTypename":null},{"name":"fullName","type":"System.String","flags":{"value__":0},"fixedBufferLength":0,"fixedBufferTypename":null},{"name":"resultState","type":"System.String","flags":{"value__":0},"fixedBufferLength":0,"fixedBufferTypename":null},{"name":"testStatus","type":"NUnit.Framework.Interfaces.TestStatus","flags":{"value__":0},"fixedBufferLength":0,"fixedBufferTypename":null},{"name":"duration","type":"System.Double","flags":{"value__":0},"fixedBufferLength":0,"fixedBufferTypename":null},{"name":"message","type":"System.String","flags":{"value__":0},"fixedBufferLength":0,"fixedBufferTypename":null},{"name":"stackTrace","type":"System.String","flags":{"value__":0},"fixedBufferLength":0,"fixedBufferTypename":null},{"name":"assertCount","type":"System.Int32","flags":{"value__":0},"fixedBufferLength":0,"fixedBufferTypename":null},{"name":"failCount","type":"System.Int32","flags":{"value__":0},"fixedBufferLength":0,"fixedBufferTypename":null},{"name":"passCount","type":"System.Int32","flags":{"value__":0},"fixedBufferLength":0,"fixedBufferTypename":null},{"name":"skipCount","type":"System.Int32","flags":{"value__":0},"fixedBufferLength":0,"fixedBufferTypename":null},{"name":"inconclusiveCount","type":"System.Int32","flags":{"value__":0},"fixedBufferLength":0,"fixedBufferTypename":null},{"name":"hasChildren","type":"System.Boolean","flags":{"value__":0},"fixedBufferLength":0,"fixedBufferTypename":null},{"name":"output","type":"System.String","flags":{"value__":0},"fixedBufferLength":0,"fixedBufferTypename":null},{"name":"xml","type":"System.String","flags":{"value__":0},"fixedBufferLength":0,"fixedBufferTypename":null},{"name":"childrenIds","type":"System.String[]","flags":{"value__":0},"fixedBufferLength":0,"fixedBufferTypename":null}]},{"className":"UnityEngine.TestRunner.TestLaunchers.RemoteTestResultDataWithTestData","fieldInfos":[{"name":"results","type":"UnityEngine.TestRunner.TestLaunchers.RemoteTestResultData[]","flags":{"value__":0},"fixedBufferLength":0,"fixedBufferTypename":null},{"name":"tests","type":"UnityEngine.TestRunner.TestLaunchers.RemoteTestData[]","flags":{"value__":0},"fixedBufferLength":0,"fixedBufferTypename":null}]},{"className":"UnityEngine.TestTools.BeforeAfterTestCommandState","fieldInfos":[{"name":"NextBeforeStepIndex","type":"System.Int32","flags":{"value__":0},"fixedBufferLength":0,"fixedBufferTypename":null},{"name":"NextBeforeStepPc","type":"System.Int32","flags":{"value__":0},"fixedBufferLength":0,"fixedBufferTypename":null},{"name":"NextAfterStepIndex","type":"System.Int32","flags":{"value__":0},"fixedBufferLength":0,"fixedBufferTypename":null},{"name":"NextAfterStepPc","type":"System.Int32","flags":{"value__":0},"fixedBufferLength":0,"fixedBufferTypename":null},{"name":"TestHasRun","type":"System.Boolean","flags":{"value__":0},"fixedBufferLength":0,"fixedBufferTypename":null},{"name":"CurrentTestResultStatus","type":"NUnit.Framework.Interfaces.TestStatus","flags":{"value__":0},"fixedBufferLength":0,"fixedBufferTypename":null},{"name":"CurrentTestResultLabel","type":"System.String","flags":{"value__":0},"fixedBufferLength":0,"fixedBufferTypename":null},{"name":"CurrentTestResultSite","type":"NUnit.Framework.Interfaces.FailureSite","flags":{"value__":0},"fixedBufferLength":0,"fixedBufferTypename":null},{"name":"CurrentTestMessage","type":"System.String","flags":{"value__":0},"fixedBufferLength":0,"fixedBufferTypename":null},{"name":"CurrentTestStrackTrace","type":"System.String","flags":{"value__":0},"fixedBufferLength":0,"fixedBufferTypename":null},{"name":"TestAfterStarted","type":"System.Boolean","flags":{"value__":0},"fixedBufferLength":0,"fixedBufferTypename":null},{"name":"Timestamp","type":"System.Int64","flags":{"value__":0},"fixedBufferLength":0,"fixedBufferTypename":null}]},{"className":"UnityEngine.TestTools.EnumerableTestState","fieldInfos":[{"name":"Repeat","type":"System.Int32","flags":{"value__":0},"fixedBufferLength":0,"fixedBufferTypename":null},{"name":"Retry","type":"System.Int32","flags":{"value__":0},"fixedBufferLength":0,"fixedBufferTypename":null}]},{"className":"UnityEngine.TestTools.Logging.LogMatch","fieldInfos":[{"name":"m_UseRegex","type":"System.Boolean","flags":{"value__":0},"fixedBufferLength":0,"fixedBufferTypename":null},{"name":"m_Message","type":"System.String","flags":{"value__":0},"fixedBufferLength":0,"fixedBufferTypename":null},{"name":"m_MessageRegex","type":"System.String","flags":{"value__":0},"fixedBufferLength":0,"fixedBufferTypename":null},{"name":"m_LogType","type":"System.String","flags":{"value__":0},"fixedBufferLength":0,"fixedBufferTypename":null}]},{"className":"UnityEngine.TestTools.TestRunner.TestFinishedEvent","fieldInfos":[]},{"className":"UnityEngine.TestTools.TestRunner.TestStartedEvent","fieldInfos":[]},{"className":"UnityEngine.TestTools.TestRunner.RunFinishedEvent","fieldInfos":[]},{"className":"UnityEngine.TestTools.TestRunner.RunStartedEvent","fieldInfos":[]},{"className":"UnityEngine.TestTools.TestRunner.PlaymodeTestsController","fieldInfos":[{"name":"m_AssembliesWithTests","type":"System.Collections.Generic.List`1[System.String]","flags":{"value__":0},"fixedBufferLength":0,"fixedBufferTypename":null},{"name":"testStartedEvent","type":"UnityEngine.TestTools.TestRunner.TestStartedEvent","flags":{"value__":0},"fixedBufferLength":0,"fixedBufferTypename":null},{"name":"testFinishedEvent","type":"UnityEngine.TestTools.TestRunner.TestFinishedEvent","flags":{"value__":0},"fixedBufferLength":0,"fixedBufferTypename":null},{"name":"runStartedEvent","type":"UnityEngine.TestTools.TestRunner.RunStartedEvent","flags":{"value__":0},"fixedBufferLength":0,"fixedBufferTypename":null},{"name":"runFinishedEvent","type":"UnityEngine.TestTools.TestRunner.RunFinishedEvent","flags":{"value__":0},"fixedBufferLength":0,"fixedBufferTypename":null},{"name":"settings","type":"UnityEngine.TestTools.TestRunner.PlaymodeTestsControllerSettings","flags":{"value__":0},"fixedBufferLength":0,"fixedBufferTypename":null}]},{"className":"UnityEngine.TestTools.TestRunner.PlaymodeTestsControllerSettings","fieldInfos":[{"name":"filters","type":"UnityEngine.TestTools.TestRunner.GUI.RuntimeTestRunnerFilter[]","flags":{"value__":0},"fixedBufferLength":0,"fixedBufferTypename":null},{"name":"sceneBased","type":"System.Boolean","flags":{"value__":0},"fixedBufferLength":0,"fixedBufferTypename":null},{"name":"originalScene","type":"System.String","flags":{"value__":0},"fixedBufferLength":0,"fixedBufferTypename":null},{"name":"bootstrapScene","type":"System.String","flags":{"value__":0},"fixedBufferLength":0,"fixedBufferTypename":null}]},{"className":"UnityEngine.TestTools.TestRunner.GUI.RuntimeTestRunnerFilter","fieldInfos":[{"name":"assemblyNames","type":"System.String[]","flags":{"value__":0},"fixedBufferLength":0,"fixedBufferTypename":null},{"name":"groupNames","type":"System.String[]","flags":{"value__":0},"fixedBufferLength":0,"fixedBufferTypename":null},{"name":"categoryNames","type":"System.String[]","flags":{"value__":0},"fixedBufferLength":0,"fixedBufferTypename":null},{"name":"testNames","type":"System.String[]","flags":{"value__":0},"fixedBufferLength":0,"fixedBufferTypename":null},{"name":"synchronousOnly","type":"System.Boolean","flags":{"value__":0},"fixedBufferLength":0,"fixedBufferTypename":null}]},{"className":"UnityEngine.TestTools.TestRunner.Callbacks.PlayModeRunnerCallback","fieldInfos":[]},{"className":"UnityEngine.TestTools.TestRunner.Callbacks.PlayerQuitHandler","fieldInfos":[]},{"className":"UnityEngine.TestTools.TestRunner.Callbacks.RemoteTestResultSender","fieldInfos":[]},{"className":"UnityEngine.TestTools.TestRunner.Callbacks.TestResultRendererCallback","fieldInfos":[]}]},{"name":"nunit.framework","path":"C:\\Users\\merli\\Desktop\\Unity3D_And_Node.JS_Multi-Player_English\\Client\\Library\\PackageCache\\com.unity.ext.nunit@1.0.6\\net35\\unity-custom\\nunit.framework.dll","types":[{"className":"NUnit.Framework.ResultStateException","fieldInfos":[]},{"className":"NUnit.Framework.AssertionException","fieldInfos":[]},{"className":"NUnit.Framework.IgnoreException","fieldInfos":[]},{"className":"NUnit.Framework.InconclusiveException","fieldInfos":[]},{"className":"NUnit.Framework.SuccessException","fieldInfos":[]},{"className":"NUnit.Framework.Internal.InvalidDataSourceException","fieldInfos":[]},{"className":"NUnit.Framework.Internal.InvalidTestFixtureException","fieldInfos":[]},{"className":"NUnit.Framework.Internal.NUnitException","fieldInfos":[]},{"className":"NUnit.Framework.Internal.RuntimeFramework","fieldInfos":[]},{"className":"NUnit.Framework.Internal.TestFilter","fieldInfos":[]},{"className":"NUnit.Framework.Internal.TestFilter+EmptyFilter","fieldInfos":[]},{"className":"NUnit.Framework.Internal.Filters.PropertyFilter","fieldInfos":[]},{"className":"NUnit.Framework.Internal.Filters.ValueMatchFilter","fieldInfos":[]},{"className":"NUnit.Framework.Internal.Filters.TestNameFilter","fieldInfos":[]},{"className":"NUnit.Framework.Internal.Filters.ClassNameFilter","fieldInfos":[]},{"className":"NUnit.Framework.Internal.Filters.MethodNameFilter","fieldInfos":[]},{"className":"NUnit.Framework.Internal.Filters.IdFilter","fieldInfos":[]},{"className":"NUnit.Framework.Internal.Filters.AndFilter","fieldInfos":[]},{"className":"NUnit.Framework.Internal.Filters.CategoryFilter","fieldInfos":[]},{"className":"NUnit.Framework.Internal.Filters.NotFilter","fieldInfos":[]},{"className":"NUnit.Framework.Internal.Filters.OrFilter","fieldInfos":[]},{"className":"NUnit.Framework.Internal.Filters.FullNameFilter","fieldInfos":[]}]}]}
